thsl/__init__.py
thsl/__version__.py
thsl/exceptions.py
thsl/src/__init__.py
thsl/src/abstract_syntax_tree.py
thsl/src/compiler.py
thsl/src/grammar.py
thsl/src/lexer.py
thsl/src/parser.py
thsl-0.1.3.dist-info/WHEEL
thsl-0.1.3.dist-info/METADATA
thsl-0.1.3.dist-info/licenses/LICENSE.txt
thsl-0.1.3.dist-info/RECORD
