Metadata-Version: 2.1
Name: thsl
Version: 0.1.3
Summary: A typed configuration language
License: MIT
Author-email: Anthony Post <post.anthony@icloud.com>
Requires-Python: >=3.10
Requires-Dist: python-dateutil==2.8.2
Requires-Dist: semantic-version==2.8.5
Requires-Dist: tempora==4.1.1
